assignment2/basics-modules/full_subtractor.v
module full_subtractor(
    input a,
    input b,
    input bin,
    output diff,
    output bout
);

assign diff = a ^ b ^ bin;
assign bout = (~a & b) | (~(a ^ b) & bin);

endmodule

assignment2/basics-testbenches/full_subtractor_tb.v
`timescale 1ns/1ps

module full_subtractor_tb;

reg a, b, bin;
wire diff, bout;

full_subtractor uut (
    .a(a),
    .b(b),
    .bin(bin),
    .diff(diff),
    .bout(bout)
);

initial begin

    // Create waveform file
    $dumpfile("waveforms/full_subtractor.vcd");
    $dumpvars(0, full_subtractor_tb);

    // Test cases

    a = 0; b = 0; bin = 0;
    #10;

    a = 0; b = 0; bin = 1;
    #10;

    a = 0; b = 1; bin = 0;
    #10;

    a = 0; b = 1; bin = 1;
    #10;

    a = 1; b = 0; bin = 0;
    #10;

    a = 1; b = 0; bin = 1;
    #10;

    a = 1; b = 1; bin = 0;
    #10;

    a = 1; b = 1; bin = 1;
    #10;

    $finish;

end

endmodule

assignment2/waveforms/full_subtractor.vcd
$date
	Wed May 27 18:47:17 2026
$end
$version
	Icarus Verilog
$end
$timescale
	1ps
$end
$scope module full_subtractor_tb $end
$var wire 1 ! diff $end
$var wire 1 " bout $end
$var reg 1 # a $end
$var reg 1 $ b $end
$var reg 1 % bin $end
$scope module uut $end
$var wire 1 # a $end
$var wire 1 $ b $end
$var wire 1 % bin $end
$var wire 1 " bout $end
$var wire 1 ! diff $end
$upscope $end
$upscope $end
$enddefinitions $end
$comment Show the parameter values. $end
$dumpall
$end
#0
$dumpvars
0%
0$
0#
0"
0!
$end
#10000
1"
1!
1%
#20000
0%
1$
#30000
0!
1%
#40000
0"
1!
0%
0$
1#
#50000
0!
1%
#60000
0%
1$
#70000
1"
1!
1%
