assignment2/basics-modules/full_adder.v
module full_adder(
    input a,
    input b,
    input cin,
    output sum,
    output cout
    
);

    assign sum = a ^ b ^ cin;
    assign cout = (a & b) | (cin & (a ^ b));

endmodule

assignment2/basics-testbenches/full_adder_tb.v
`timescale 1ns / 1ps

module full_adder_tb;
    reg a;
    reg b;
    reg cin;
    wire sum;
    wire cout;

    full_adder uut (
        .a(a),
        .b(b),
        .cin(cin),
        .sum(sum),
        .cout(cout)
    );

    initial begin
        $dumpfile("waveforms/full_adder.vcd");
        $dumpvars(0, full_adder_tb);

        a = 0; b = 0; cin = 0;
        #10;
        a = 0; b = 1; cin = 0;
        #10;
        a = 1; b = 0; cin = 0;
        #10;
        a = 1; b = 1; cin = 0;
        #10;
        a = 0; b = 0; cin = 1;
        #10;
        a = 0; b = 1; cin = 1;
        #10;
        a = 1; b = 0; cin = 1;
        #10;
        a = 1; b = 1; cin = 1;
        #10;

        $finish;
    end
endmodule

assignment2/waveforms/full_adder.vcd
$date
	Wed May 27 18:21:31 2026
$end
$version
	Icarus Verilog
$end
$timescale
	1ps
$end
$scope module full_adder_tb $end
$var wire 1 ! sum $end
$var wire 1 " cout $end
$var reg 1 # a $end
$var reg 1 $ b $end
$var reg 1 % cin $end
$scope module uut $end
$var wire 1 # a $end
$var wire 1 $ b $end
$var wire 1 % cin $end
$var wire 1 " cout $end
$var wire 1 ! sum $end
$upscope $end
$upscope $end
$enddefinitions $end
$comment Show the parameter values. $end
$dumpall
$end
#0
$dumpvars
0%
0$
0#
0"
0!
$end
#10000
1!
1$
#20000
0$
1#
#30000
0!
1"
1$
#40000
0"
1!
1%
0$
0#
#50000
1"
0!
1$
#60000
0$
1#
#70000
1!
1$
