assignment3/Gray_to_sevensegment.v
module gray_to_7segment(
    input  wire A,
    input  wire B,
    input  wire C,
    output wire a,
    output wire b,
    output wire c,
    output wire d,
    output wire e,
    output wire f,
    output wire g
);

 assign a = (A & B) | (A & C) | (~B & ~C) | (B & C);
   
   assign b = (~A) | (~B & ~C) | (B & C);
   
   assign c = A | (~B) | C;
   
   assign d = (A & B & ~C) |
              (~A & B) |
              (A & ~B & C) |
              (~A & ~B & ~C);
   
   assign e = (B & ~C) |
              (~A & ~B & ~C);
   
   assign f = (A & ~B) |
              (A & B & ~C) |
              (~A & ~B & ~C);
   
   assign g = (A & B) |
              (~A & B) |
              (A & ~B & C);

endmodule

assignment3/Gray_to_sevensegment_tb.v
`timescale 1ns/1ps

module Gray_to_sevensegment_tb;

reg A, B, C;

wire a, b, c, d, e, f, g;

gray_to_7segment uut (
    .A(A),
    .B(B),
    .C(C),
    .a(a),
    .b(b),
    .c(c),
    .d(d),
    .e(e),
    .f(f),
    .g(g)
);

  

    initial begin
    
        $dumpfile("Gray_to_sevensegment.vcd");
        $dumpvars(0,Gray_to_sevensegment_tb);
    
    
        $monitor("A=%b B=%b C=%b -> a=%b b=%b c=%b d=%b e=%b f=%b g=%b",
                  A,B,C,a,b,c,d,e,f,g);
    
        A=0; B=0; C=0; #10;
        A=0; B=0; C=1; #10;
        A=0; B=1; C=1; #10;
        A=0; B=1; C=0; #10;
        A=1; B=1; C=0; #10;
        A=1; B=1; C=1; #10;
        A=1; B=0; C=1; #10;
        A=1; B=0; C=0; #10;
    
        $finish;
    
    end

endmodule

assignment3/Gray_to_sevensegment.vcd
$date
	Thu May 28 18:46:28 2026
$end
$version
	Icarus Verilog
$end
$timescale
	1ps
$end
$scope module Gray_to_sevensegment_tb $end
$var wire 1 ! g $end
$var wire 1 " f $end
$var wire 1 # e $end
$var wire 1 $ d $end
$var wire 1 % c $end
$var wire 1 & b $end
$var wire 1 ' a $end
$var reg 1 ( A $end
$var reg 1 ) B $end
$var reg 1 * C $end
$scope module uut $end
$var wire 1 ( A $end
$var wire 1 ) B $end
$var wire 1 * C $end
$var wire 1 ' a $end
$var wire 1 & b $end
$var wire 1 % c $end
$var wire 1 $ d $end
$var wire 1 # e $end
$var wire 1 " f $end
$var wire 1 ! g $end
$upscope $end
$upscope $end
$enddefinitions $end
$comment Show the parameter values. $end
$dumpall
$end
#0
$dumpvars
0*
0)
0(
1'
1&
1%
1$
1#
1"
0!
$end
#10000
0'
0$
0#
0"
1*
#20000
1$
1!
1'
1)
#30000
1#
0'
0%
0*
#40000
1'
1"
0&
1%
1(
#50000
0$
0"
0#
1&
1*
#60000
1$
1"
0&
0)
#70000
1&
0$
0!
0*
